daxia.py
daxiamcp-1.0.0.dist-info/METADATA
daxiamcp-1.0.0.dist-info/WHEEL
daxiamcp-1.0.0.dist-info/entry_points.txt
daxiamcp-1.0.0.dist-info/top_level.txt
daxiamcp-1.0.0.dist-info/RECORD
