Metadata-Version: 2.4
Name: daxiamcp
Version: 1.0.0
Summary: Daxia OpenAPI Client based MCP
Requires-Python: >=3.12
Requires-Dist: fastmcp>=2.14.0
Requires-Dist: httpx>=0.28.1
Requires-Dist: requests>=2.32.5
